parametrize/__init__.py
parametrize/parametrize.py
parametrize/utils.py
parametrize-0.1.0.dist-info/WHEEL
parametrize-0.1.0.dist-info/METADATA
parametrize-0.1.0.dist-info/RECORD
