Metadata-Version: 2.1
Name: parametrize
Version: 0.1.0
Summary: Drop-in @pytest.mark.parametrize replacement working with unittest.TestCase
Home-page: https://github.com/MrMrRobat/parametrize/
License: MIT
Author: MrMrRobat
Author-email: appkiller16@gmail.com
Requires-Python: >=3.6.2,<4.0.0
Classifier: Development Status :: 3 - Alpha
Classifier: Framework :: Pytest
Classifier: Intended Audience :: Developers
Classifier: License :: OSI Approved :: MIT License
Classifier: Operating System :: OS Independent
Classifier: Programming Language :: Python
Classifier: Programming Language :: Python :: 3
Classifier: Programming Language :: Python :: 3 :: Only
Classifier: Programming Language :: Python :: 3.6
Classifier: Programming Language :: Python :: 3.7
Classifier: Programming Language :: Python :: 3.8
Classifier: Programming Language :: Python :: 3.9
Classifier: Programming Language :: Python :: Implementation :: CPython
Classifier: Topic :: Software Development :: Libraries
Classifier: Topic :: Software Development :: Testing
Classifier: Topic :: Software Development :: Testing :: Unit
Classifier: Typing :: Typed
Project-URL: Repository, https://github.com/MrMrRobat/parametrize/
